{
  "todos": [
    {
      "id": 1,
      "date": 1579878000000,
      "title": "title",
      "message": "What Today todo",
      "done": false,
      "allday": true
    },
    {
      "id": 2,
      "date": 1579935720000,
      "title": "GOGO",
      "message": "Let's go",
      "done": false,
      "allday": false
    },
    {
      "id": 3,
      "date": 1579950480000,
      "title": "AA",
      "message": "ff",
      "done": true,
      "allday": false
    },
    {
      "id": 4,
      "date": 1579878000000,
      "title": "sadfasdfasdf",
      "message": "asdfasdfasdfasdfsdaf",
      "done": true,
      "allday": false
    },
    {
      "id": 5,
      "date": 1579878000000,
      "title": "Kora",
      "message": "Hora",
      "done": true,
      "allday": false
    },
    {
      "date": 1579878000000,
      "title": "KoAAAAAra",
      "message": "AAA",
      "done": true,
      "allday": false,
      "id": 6
    },
    {
      "date": 1734534000000,
      "title": "NEW!",
      "message": "sadfsadf",
      "done": true,
      "allday": true,
      "id": 7
    },
    {
      "date": 1734534000000,
      "title": "sadfsadf",
      "message": "sadfsadfsadfdsaf",
      "done": false,
      "allday": true,
      "id": 8
    },
    {
      "date": 1734534000000,
      "title": "AAAAAAAAAAAA",
      "message": "AAAAAAAAAAAA",
      "done": false,
      "allday": true,
      "id": 9
    },
    {
      "date": 1734588180000,
      "title": "33",
      "message": "33",
      "done": false,
      "allday": false,
      "id": 10
    },
    {
      "date": 1734534000000,
      "title": "NEWONW",
      "message": "NEONWE",
      "done": true,
      "allday": false,
      "id": 11
    },
    {
      "date": 1735225200000,
      "title": "HAHAHA",
      "message": "dsafsadfsadfsadfsadfdsfads",
      "done": false,
      "allday": false,
      "id": 13
    }
  ],
  "users": [
    {
      "username": "John Doe",
      "id": "johndoe1234",
      "password": "johndoe1234"
    },
    {
      "username": "Jane Doe",
      "id": "janedoe1234",
      "password": "janedoe1234"
    },
    {
      "username": "Babby Doe",
      "id": "babydoe1234",
      "password": "babydoe1234"
    }
  ]
}